flask_restforms/__init__.py
flask_restforms/main.py
Flask_RestForms-0.1.2.dist-info/LICENSE
Flask_RestForms-0.1.2.dist-info/METADATA
Flask_RestForms-0.1.2.dist-info/WHEEL
Flask_RestForms-0.1.2.dist-info/top_level.txt
Flask_RestForms-0.1.2.dist-info/RECORD
