Metadata-Version: 2.1
Name: Flask-RestForms
Version: 0.1.2
Summary: Add REST superpowers to your Jinja templates
Home-page: https://www.github.com/alanmunguiacerda/flask-restforms/
Author: Alan Munguia Cerda
License: MIT
Keywords: FLASK,JINJA,REST,MPA
Platform: any
Classifier: Development Status :: 3 - Alpha
Classifier: Intended Audience :: Developers
Classifier: Topic :: Internet :: WWW/HTTP :: Dynamic Content
Classifier: Topic :: Software Development :: Libraries :: Python Modules
Classifier: License :: OSI Approved :: MIT License
Classifier: Environment :: Web Environment
Classifier: Operating System :: OS Independent
Classifier: Programming Language :: Python
Classifier: Programming Language :: Python :: 3.6
Classifier: Programming Language :: Python :: 3.7
Requires-Python: >= 3.6
Requires-Dist: Flask
Requires-Dist: Jinja2 (>=2.5)
